MANIFEST.in
README.rst
setup.py
docs/HISTORY.txt
docs/LICENSE.GPL
docs/LICENSE.txt
ftw/__init__.py
ftw.calendar.egg-info/PKG-INFO
ftw.calendar.egg-info/SOURCES.txt
ftw.calendar.egg-info/dependency_links.txt
ftw.calendar.egg-info/entry_points.txt
ftw.calendar.egg-info/namespace_packages.txt
ftw.calendar.egg-info/not-zip-safe
ftw.calendar.egg-info/requires.txt
ftw.calendar.egg-info/top_level.txt
ftw/calendar/__init__.py
ftw/calendar/configure.zcml
ftw/calendar/profiles.zcml
ftw/calendar/setuphandlers.py
ftw/calendar/skins.zcml
ftw/calendar/testing.py
ftw/calendar/upgrades.zcml
ftw/calendar/Extensions/install.py
ftw/calendar/browser/__init__.py
ftw/calendar/browser/calendar_config.pt
ftw/calendar/browser/calendar_config.py
ftw/calendar/browser/calendarupdateview.py
ftw/calendar/browser/calendarview.pt
ftw/calendar/browser/calendarview.py
ftw/calendar/browser/configure.zcml
ftw/calendar/browser/interfaces.py
ftw/calendar/browser/static/ftwcalendar.css
ftw/calendar/browser/static/fullcalendar.css
ftw/calendar/browser/static/fullcalendar.js
ftw/calendar/browser/static/fullcalendar.min.js
ftw/calendar/browser/static/transp.png
ftw/calendar/locales/ftw.calendar.pot
ftw/calendar/locales/cs/LC_MESSAGES/ftw.calendar.po
ftw/calendar/locales/de/LC_MESSAGES/README.txt
ftw/calendar/locales/de/LC_MESSAGES/ftw.calendar.po
ftw/calendar/locales/fr/LC_MESSAGES/ftw.calendar.po
ftw/calendar/locales/nl/LC_MESSAGES/ftw.calendar.po
ftw/calendar/profiles/base/browserlayer.xml
ftw/calendar/profiles/base/ftw.calendar_various.txt
ftw/calendar/profiles/base/metadata.xml
ftw/calendar/profiles/base/types/Collection.xml
ftw/calendar/profiles/base/types/Folder.xml
ftw/calendar/profiles/plone4/cssregistry.xml
ftw/calendar/profiles/plone4/jsregistry.xml
ftw/calendar/profiles/plone4/metadata.xml
ftw/calendar/profiles/plone4/types/Topic.xml
ftw/calendar/profiles/plone5/metadata.xml
ftw/calendar/profiles/plone5/registry.xml
ftw/calendar/profiles/uninstall-base/browserlayer.xml
ftw/calendar/profiles/uninstall-base/types/Collection.xml
ftw/calendar/profiles/uninstall-base/types/Folder.xml
ftw/calendar/profiles/uninstall-plone4/cssregistry.xml
ftw/calendar/profiles/uninstall-plone4/jsregistry.xml
ftw/calendar/profiles/uninstall-plone4/metadata.xml
