Metadata-Version: 2.1
Name: ftw.calendar
Version: 3.1.2
Summary: Calendar view based on fullcalendar
Home-page: https://github.com/4teamwork/ftw.calendar
Author: 4teamwork AG
Author-email: mailto:info@4teamwork.ch
License: GPL2
Platform: UNKNOWN
Classifier: Framework :: Plone
Classifier: Framework :: Plone :: 4.3
Classifier: Framework :: Plone :: 5.1
Classifier: Programming Language :: Python
Provides-Extra: tests
